pyJHTDB/MortonIndex.py
pyJHTDB/__init__.py
pyJHTDB/data/big_channel_Y_COOR.txt
pyJHTDB/data/channel5200_Y_COOR.txt
pyJHTDB/data/channel5200_ygrid.npy
pyJHTDB/data/channel_grid.h5
pyJHTDB/data/channel_xgrid.npy
pyJHTDB/data/channel_ygrid.npy
pyJHTDB/data/channel_zgrid.npy
pyJHTDB/data/convert.py
pyJHTDB/data/convert2.py
pyJHTDB/data/transition_bl_Y_COORD.txt
pyJHTDB/data/transition_bl_ygrid.npy
pyJHTDB/dbinfo.py
pyJHTDB/generic_splines.py
pyJHTDB/interpolator.py
pyJHTDB/lib/C/local_tools.c
pyJHTDB/lib/libJHTDB.cpython-310-darwin.so
pyJHTDB/lib/turblib/.gitignore
pyJHTDB/lib/turblib/DEMO_channelc
pyJHTDB/lib/turblib/DEMO_channelc.c
pyJHTDB/lib/turblib/DEMO_channelf
pyJHTDB/lib/turblib/DEMO_channelf.f90
pyJHTDB/lib/turblib/DEMO_getCutoutc
pyJHTDB/lib/turblib/DEMO_getCutoutc.c
pyJHTDB/lib/turblib/DEMO_getCutoutf
pyJHTDB/lib/turblib/DEMO_getCutoutf.f90
pyJHTDB/lib/turblib/DEMO_mhdc
pyJHTDB/lib/turblib/DEMO_mhdc.c
pyJHTDB/lib/turblib/DEMO_mhdf
pyJHTDB/lib/turblib/DEMO_mhdf.f90
pyJHTDB/lib/turblib/DEMO_mixingc
pyJHTDB/lib/turblib/DEMO_mixingc.c
pyJHTDB/lib/turblib/DEMO_mixingf
pyJHTDB/lib/turblib/DEMO_mixingf.f90
pyJHTDB/lib/turblib/DEMO_turbc
pyJHTDB/lib/turblib/DEMO_turbc.c
pyJHTDB/lib/turblib/DEMO_turbf
pyJHTDB/lib/turblib/DEMO_turbf.f90
pyJHTDB/lib/turblib/LICENSE-2.0.txt
pyJHTDB/lib/turblib/Makefile
pyJHTDB/lib/turblib/README.md
pyJHTDB/lib/turblib/TurbulenceService.h
pyJHTDB/lib/turblib/TurbulenceServiceSoap.nsmap
pyJHTDB/lib/turblib/soapC.c
pyJHTDB/lib/turblib/soapClient.c
pyJHTDB/lib/turblib/soapH.h
pyJHTDB/lib/turblib/soapStub.h
pyJHTDB/lib/turblib/stdsoap2.c
pyJHTDB/lib/turblib/stdsoap2.h
pyJHTDB/lib/turblib/testall
pyJHTDB/lib/turblib/turblib.c
pyJHTDB/lib/turblib/turblib.h
pyJHTDB/libJHTDB.py
pyJHTDB/misc.py
pyJHTDB/test.py
pyJHTDB/test_data.py
pyjhtdbv2-20240506.6.dist-info/LICENSE
pyjhtdbv2-20240506.6.dist-info/METADATA
pyjhtdbv2-20240506.6.dist-info/WHEEL
pyjhtdbv2-20240506.6.dist-info/RECORD
