Metadata-Version: 2.1
Name: pyjhtdbv2
Version: 20240506.6
Summary: Python wrapper for the Johns Hopkins turbulence database library
License: Apache-2.0
Author: Johns Hopkins Turbulence Database Group
Author-email: turbulence@pha.jhu.edu
Requires-Python: >=3.7,<4.0
Classifier: License :: OSI Approved :: Apache Software License
Classifier: Programming Language :: Python :: 3
Classifier: Programming Language :: Python :: 3.7
Classifier: Programming Language :: Python :: 3.8
Classifier: Programming Language :: Python :: 3.9
Classifier: Programming Language :: Python :: 3.10
Classifier: Programming Language :: Python :: 3.11
Classifier: Programming Language :: Python :: 3.12
Requires-Dist: h5py (>=2.8.0)
Requires-Dist: matplotlib (>=3.0.0)
Requires-Dist: numpy (>=1.15.0)
Requires-Dist: scipy (>=1.1.0)
Requires-Dist: sympy (>=1.2)
Requires-Dist: wurlitzer (>=2.0.2)
